mcp_server_vecx/__init__.py
mcp_server_vecx/main.py
mcp_server_vecx/mcp_server.py
mcp_server_vecx/server.py
mcp_server_vecx/settings.py
mcp_server_vecx-0.1.4.dist-info/METADATA
mcp_server_vecx-0.1.4.dist-info/WHEEL
mcp_server_vecx-0.1.4.dist-info/entry_points.txt
mcp_server_vecx-0.1.4.dist-info/RECORD
