Metadata-Version: 2.4
Name: mcp-server-vecx
Version: 0.1.4
Summary: VectorX Mcp Server
License-Expression: MIT
Requires-Python: >=3.13
Requires-Dist: fastmcp>=2.10.4
Requires-Dist: vecx>=0.33.1
